Metadata-Version: 2.1
Name: servicenow-utils
Version: 0.20
Summary: A utility module for retrieving incidents from ServiceNow
Home-page: https://github.com/reese-001/servicenow-utils/blob/main/setup.py
License: MIT
Keywords: servicenow incidents utility
License-File: LICENSE.md
